clipthread/__init__.py
clipthread/main.py
clipthread-0.0.2.dist-info/METADATA
clipthread-0.0.2.dist-info/WHEEL
clipthread-0.0.2.dist-info/licenses/LICENSE
clipthread-0.0.2.dist-info/RECORD
